phone_number_validator_bobjones1024/__init__.py
phone_number_validator_bobjones1024/validator.py
phone_number_validator_bobjones1024-0.1.2.dist-info/METADATA
phone_number_validator_bobjones1024-0.1.2.dist-info/WHEEL
phone_number_validator_bobjones1024-0.1.2.dist-info/RECORD
